mindfoundry.client.analyze-1.21.0-py3.9-nspkg.pth
mindfoundry/client/analyze/__init__.py
mindfoundry/client/analyze/_version.py
mindfoundry/client/analyze/client.py
mindfoundry/client/analyze/project_api_swagger_client.py
mindfoundry/client/analyze/sklearn_client/__init__.py
mindfoundry/client/analyze/sklearn_client/connection.py
mindfoundry/client/analyze/sklearn_client/data_set.py
mindfoundry/client/analyze/sklearn_client/prediction.py
mindfoundry/client/analyze/sklearn_client/test.py
mindfoundry/client/analyze/sklearn_client/model/__init__.py
mindfoundry/client/analyze/sklearn_client/model/load_model.py
mindfoundry/client/analyze/sklearn_client/model/serialization.py
mindfoundry/client/analyze/sklearn_client/model/classifier/__init__.py
mindfoundry/client/analyze/sklearn_client/model/classifier/analyze_classifier.py
mindfoundry/client/analyze/sklearn_client/model/classifier/local.py
mindfoundry/client/analyze/sklearn_client/model/regressor/__init__.py
mindfoundry/client/analyze/sklearn_client/model/regressor/analyze_regressor.py
mindfoundry/client/analyze/sklearn_client/model/regressor/local.py
mindfoundry/client/analyze/sklearn_client/model/shared/__init__.py
mindfoundry/client/analyze/sklearn_client/model/shared/analyze_model.py
mindfoundry/client/analyze/sklearn_client/model/shared/base.py
mindfoundry/client/analyze/sklearn_client/model/shared/local.py
mindfoundry/client/analyze/sklearn_client/model/shared/remote.py
mindfoundry/client/analyze/swagger/__init__.py
mindfoundry/client/analyze/swagger/client.py
mindfoundry/client/analyze/swagger/py.typed
mindfoundry/client/analyze/swagger/types.py
mindfoundry/client/analyze/swagger/api/__init__.py
mindfoundry/client/analyze/swagger/api/ap_is/__init__.py
mindfoundry/client/analyze/swagger/api/ap_is/create_model_api.py
mindfoundry/client/analyze/swagger/api/ap_is/create_model_api_client.py
mindfoundry/client/analyze/swagger/api/ap_is/create_pipeline_api.py
mindfoundry.client.analyze-1.21.0.dist-info/LICENSE
mindfoundry.client.analyze-1.21.0.dist-info/METADATA
mindfoundry.client.analyze-1.21.0.dist-info/WHEEL
mindfoundry.client.analyze-1.21.0.dist-info/namespace_packages.txt
mindfoundry.client.analyze-1.21.0.dist-info/top_level.txt
mindfoundry.client.analyze-1.21.0.dist-info/RECORD
