Metadata-Version: 2.1
Name: mindfoundry.client.analyze
Version: 1.21.0
Summary: Mind Foundry Analyze Python Client
Home-page: https://www.mindfoundry.ai/platform
Author: Mind Foundry Ltd
Author-email: support@mindfoundry.ai
License: MIT
Platform: UNKNOWN
Classifier: Development Status :: 3 - Alpha
Classifier: Intended Audience :: Developers
Classifier: Topic :: Scientific/Engineering :: Artificial Intelligence
Classifier: Programming Language :: Python :: 3
Classifier: License :: OSI Approved :: MIT License
Classifier: Operating System :: OS Independent
License-File: LICENSE
Requires-Dist: attrs
Requires-Dist: httpx (<0.23.1,>=0.22)
Requires-Dist: pandas
Requires-Dist: pyarrow
Requires-Dist: requests
Provides-Extra: all
Requires-Dist: coverage ; extra == 'all'
Requires-Dist: pytest-freezegun ; extra == 'all'
Requires-Dist: pre-commit ; extra == 'all'
Requires-Dist: pylint-pytest ; extra == 'all'
Requires-Dist: tox ; extra == 'all'
Requires-Dist: freezegun ; extra == 'all'
Requires-Dist: black ; extra == 'all'
Requires-Dist: mypy ; extra == 'all'
Requires-Dist: isort ; extra == 'all'
Requires-Dist: pytest-httpx ; extra == 'all'
Requires-Dist: check-manifest ; extra == 'all'
Requires-Dist: pylint ; extra == 'all'
Requires-Dist: pytest ; extra == 'all'
Requires-Dist: requests-toolbelt ; extra == 'all'
Provides-Extra: dev
Requires-Dist: black ; extra == 'dev'
Requires-Dist: check-manifest ; extra == 'dev'
Requires-Dist: coverage ; extra == 'dev'
Requires-Dist: freezegun ; extra == 'dev'
Requires-Dist: isort ; extra == 'dev'
Requires-Dist: mypy ; extra == 'dev'
Requires-Dist: pre-commit ; extra == 'dev'
Requires-Dist: pylint ; extra == 'dev'
Requires-Dist: pytest ; extra == 'dev'
Requires-Dist: pytest-freezegun ; extra == 'dev'
Requires-Dist: pytest-httpx ; extra == 'dev'
Requires-Dist: pylint-pytest ; extra == 'dev'
Requires-Dist: requests-toolbelt ; extra == 'dev'
Requires-Dist: tox ; extra == 'dev'
